{
    "@class": "com.kony.gen.viz.model.component.KVizButton",
    "DNDConfig": null,
    "_height_": {
        "type": "string",
        "value": "12%"
    },
    "_left_": {
        "type": "string",
        "value": "0dp"
    },
    "_margin_": [
        6,
        6,
        6,
        6
    ],
    "_padding_": [
        0,
        0,
        0,
        0
    ],
    "_skin_": "s1199aded57e45de9297acd23f0da22d",
    "_text_": "OK",
    "_top_": {
        "type": "string",
        "value": "4%"
    },
    "_width_": {
        "type": "string",
        "value": "60%"
    },
    "canUpdateUI": true,
    "centerx": {
        "type": "string",
        "value": "50%"
    },
    "containerweight": 100,
    "contentalignment": 5,
    "disabledSkins": {
        "focusSkin": "s7d0ac6715754c04ab097928490d1064"
    },
    "displaytext": true,
    "id": "btnDeleteFailure",
    "info": null,
    "iscustomlayout": false,
    "isvisible": true,
    "kuid": "c449dbc4aa3343d1976003f33d189252",
    "name": "kony.ui.Button",
    "parent": "flxDeleteMainFailure",
    "pf": "frmPostLogin",
    "retaincontentalignment": false,
    "retainflexpositionproperties": false,
    "texti18n": "i18n.hid.common.ok",
    "wType": "Button",
    "zindex": 1
}